dicey/__init__.py
dicey/__main__.py
dicey/dicey.lark
dicey/dieparser.py
dicey/dietransformer.py
dicey-2.0.7.dist-info/LICENSE
dicey-2.0.7.dist-info/METADATA
dicey-2.0.7.dist-info/WHEEL
dicey-2.0.7.dist-info/entry_points.txt
dicey-2.0.7.dist-info/top_level.txt
dicey-2.0.7.dist-info/RECORD
