Metadata-Version: 2.1
Name: dicey
Version: 2.0.7
Summary: UNKNOWN
Home-page: https://github.com/gnullbyte/dicey
Author: Chase Franklin
Author-email: gnullbyte@gmail.com
License: UNKNOWN
Platform: UNKNOWN
Classifier: Programming Language :: Python :: 3
Classifier: License :: OSI Approved :: MIT License
Classifier: Operating System :: POSIX :: Linux
Requires-Dist: lark-parser
Requires-Dist: docopt
